<?xml version="1.0" encoding="UTF-8"?>

<!-- generated on 02/12/21 16:32:59 by Eclipse SUMO netedit Version 1.7.0
<configuration xmlns:xsi="http://www.w3.org/2001/XMLSchema-instance" xsi:noNamespaceSchemaLocation="http://sumo.dlr.de/xsd/netconvertConfiguration.xsd">

    <input>
        <sumo-net-file value="E:\escape_docs\Code\itms\hello\ravindra\lanePlus\osm.net.xml"/>
    </input>

    <output>
        <output-file value="E:\escape_docs\Code\itms\hello\ravindra\lanePlus\osm.net.xml"/>
        <output.street-names value="true"/>
    </output>

    <processing>
        <geometry.min-radius.fix.railways value="false"/>
        <geometry.max-grade.fix value="false"/>
        <offset.disable-normalization value="true"/>
        <lefthand value="true"/>
    </processing>

    <junctions>
        <no-turnarounds value="true"/>
        <junctions.corner-detail value="5"/>
        <junctions.limit-turn-speed value="5.5"/>
        <rectangular-lane-cut value="false"/>
    </junctions>

    <pedestrian>
        <walkingareas value="false"/>
    </pedestrian>

    <report>
        <aggregate-warnings value="5"/>
    </report>

</configuration>
-->

<net version="1.6" junctionCornerDetail="5" lefthand="true" limitTurnSpeed="5.50" xmlns:xsi="http://www.w3.org/2001/XMLSchema-instance" xsi:noNamespaceSchemaLocation="http://sumo.dlr.de/xsd/net_file.xsd">

    <location netOffset="-228603.79,-1923026.94" convBoundary="0.00,0.00,5037.24,6455.61" origBoundary="78.445052,17.377221,78.493235,17.434916" projParameter="+proj=utm +zone=44 +ellps=WGS84 +datum=WGS84 +units=m +no_defs"/>

    <type id="highway.bridleway" priority="1" numLanes="1" speed="2.78" allow="pedestrian" oneway="1" width="2.00"/>
    <type id="highway.bus_guideway" priority="1" numLanes="1" speed="27.78" allow="bus" oneway="1"/>
    <type id="highway.cycleway" priority="1" numLanes="1" speed="8.33" allow="bicycle" oneway="0" width="1.00"/>
    <type id="highway.footway" priority="1" numLanes="1" speed="2.78" allow="pedestrian" oneway="1" width="2.00"/>
    <type id="highway.ford" priority="1" numLanes="1" speed="2.78" allow="army" oneway="0"/>
    <type id="highway.living_street" priority="2" numLanes="1" speed="2.78" disallow="tram rail_urban rail rail_electric rail_fast ship" oneway="0"/>
    <type id="highway.motorway" priority="14" numLanes="2" speed="39.44" allow="private emergency authority army vip passenger hov taxi bus coach delivery truck trailer motorcycle evehicle custom1 custom2" oneway="1"/>
    <type id="highway.motorway_link" priority="9" numLanes="1" speed="22.22" allow="private emergency authority army vip passenger hov taxi bus coach delivery truck trailer motorcycle evehicle custom1 custom2" oneway="1"/>
    <type id="highway.path" priority="1" numLanes="1" speed="2.78" allow="pedestrian bicycle" oneway="1" width="2.00"/>
    <type id="highway.pedestrian" priority="1" numLanes="1" speed="2.78" allow="pedestrian" oneway="1" width="2.00"/>
    <type id="highway.primary" priority="12" numLanes="2" speed="27.78" disallow="tram rail_urban rail rail_electric rail_fast ship" oneway="0"/>
    <type id="highway.primary_link" priority="7" numLanes="1" speed="22.22" disallow="tram rail_urban rail rail_electric rail_fast ship" oneway="0"/>
    <type id="highway.raceway" priority="15" numLanes="2" speed="83.33" allow="vip" oneway="0"/>
    <type id="highway.residential" priority="3" numLanes="1" speed="13.89" disallow="tram rail_urban rail rail_electric rail_fast ship" oneway="0"/>
    <type id="highway.secondary" priority="11" numLanes="1" speed="27.78" disallow="tram rail_urban rail rail_electric rail_fast ship" oneway="0"/>
    <type id="highway.secondary_link" priority="6" numLanes="1" speed="22.22" disallow="tram rail_urban rail rail_electric rail_fast ship" oneway="0"/>
    <type id="highway.service" priority="1" numLanes="1" speed="5.56" allow="pedestrian delivery bicycle" oneway="0"/>
    <type id="highway.stairs" priority="1" numLanes="1" speed="1.39" allow="pedestrian" oneway="1" width="2.00"/>
    <type id="highway.step" priority="1" numLanes="1" speed="1.39" allow="pedestrian" oneway="1" width="2.00"/>
    <type id="highway.steps" priority="1" numLanes="1" speed="1.39" allow="pedestrian" oneway="1" width="2.00"/>
    <type id="highway.tertiary" priority="10" numLanes="1" speed="22.22" disallow="tram rail_urban rail rail_electric rail_fast ship" oneway="0"/>
    <type id="highway.tertiary_link" priority="5" numLanes="1" speed="22.22" disallow="tram rail_urban rail rail_electric rail_fast ship" oneway="0"/>
    <type id="highway.track" priority="1" numLanes="1" speed="5.56" allow="pedestrian motorcycle moped bicycle" oneway="0"/>
    <type id="highway.trunk" priority="13" numLanes="2" speed="27.78" disallow="pedestrian bicycle tram rail_urban rail rail_electric rail_fast ship" oneway="0"/>
    <type id="highway.trunk_link" priority="8" numLanes="1" speed="22.22" disallow="pedestrian bicycle tram rail_urban rail rail_electric rail_fast ship" oneway="0"/>
    <type id="highway.unclassified" priority="4" numLanes="1" speed="13.89" disallow="tram rail_urban rail rail_electric rail_fast ship" oneway="0"/>
    <type id="highway.unsurfaced" priority="1" numLanes="1" speed="8.33" disallow="tram rail_urban rail rail_electric rail_fast ship" oneway="0"/>
    <type id="railway.highspeed" priority="21" numLanes="1" speed="69.44" allow="rail_fast" oneway="1"/>
    <type id="railway.light_rail" priority="19" numLanes="1" speed="27.78" allow="rail_urban" oneway="1"/>
    <type id="railway.preserved" priority="16" numLanes="1" speed="27.78" allow="rail" oneway="1"/>
    <type id="railway.rail" priority="20" numLanes="1" speed="44.44" allow="rail" oneway="1"/>
    <type id="railway.subway" priority="18" numLanes="1" speed="27.78" allow="rail_urban" oneway="1"/>
    <type id="railway.tram" priority="17" numLanes="1" speed="13.89" allow="tram" oneway="1"/>

    <edge id=":2177311061_0" function="internal">
        <lane id=":2177311061_0_0" index="0" disallow="pedestrian bicycle tram rail_urban rail rail_electric rail_fast ship" speed="14.30" length="13.28" width="2.50" shape="2367.69,2880.85 2368.46,2883.99 2368.39,2886.75 2367.67,2889.79 2366.47,2893.77"/>
    </edge>
    <edge id=":2177311061_1" function="internal">
        <lane id=":2177311061_1_0" index="0" disallow="pedestrian bicycle tram rail_urban rail rail_electric rail_fast ship" speed="60.00" length="13.85" width="2.50" shape="2372.30,2881.37 2368.86,2894.48"/>
        <lane id=":2177311061_1_1" index="1" disallow="pedestrian bicycle tram rail_urban rail rail_electric rail_fast ship" speed="60.00" length="13.85" width="2.50" shape="2374.74,2881.94 2371.26,2895.19"/>
        <lane id=":2177311061_1_2" index="2" disallow="pedestrian bicycle tram rail_urban rail rail_electric rail_fast ship" speed="60.00" length="13.85" width="2.50" shape="2377.17,2882.51 2373.66,2895.91"/>
        <lane id=":2177311061_1_3" index="3" disallow="pedestrian bicycle tram rail_urban rail rail_electric rail_fast ship" speed="60.00" length="13.85" width="2.50" shape="2379.60,2883.08 2376.06,2896.62"/>
        <lane id=":2177311061_1_4" index="4" disallow="pedestrian bicycle tram rail_urban rail rail_electric rail_fast ship" speed="60.00" length="13.85" width="2.50" shape="2382.04,2883.66 2378.45,2897.33"/>
    </edge>
    <edge id=":7721233577_0" function="internal">
        <lane id=":7721233577_0_0" index="0" disallow="pedestrian bicycle tram rail_urban rail rail_electric rail_fast ship" speed="41.11" length="9.47" shape="2344.61,2874.76 2347.40,2874.57 2349.33,2874.64 2351.25,2874.80 2354.06,2874.89"/>
    </edge>
    <edge id=":7721233577_1" function="internal">
        <lane id=":7721233577_1_0" index="0" disallow="pedestrian bicycle tram rail_urban rail rail_electric rail_fast ship" speed="60.00" length="8.72" width="2.50" shape="2344.61,2874.76 2347.28,2874.22 2349.03,2873.47 2350.78,2872.70 2353.44,2872.11"/>
        <lane id=":7721233577_1_1" index="1" disallow="pedestrian bicycle tram rail_urban rail rail_electric rail_fast ship" speed="60.00" length="8.72" width="2.50" shape="2344.34,2872.28 2346.93,2871.74 2348.62,2871.00 2350.31,2870.24 2352.90,2869.66"/>
        <lane id=":7721233577_1_2" index="2" disallow="pedestrian bicycle tram rail_urban rail rail_electric rail_fast ship" speed="60.00" length="8.72" width="2.50" shape="2344.07,2869.79 2346.58,2869.27 2348.21,2868.53 2349.85,2867.78 2352.35,2867.21"/>
        <lane id=":7721233577_1_3" index="3" disallow="pedestrian bicycle tram rail_urban rail rail_electric rail_fast ship" speed="60.00" length="8.72" width="2.50" shape="2343.80,2867.31 2346.23,2866.79 2347.81,2866.06 2349.38,2865.32 2351.81,2864.76"/>
        <lane id=":7721233577_1_4" index="4" disallow="pedestrian bicycle tram rail_urban rail rail_electric rail_fast ship" speed="60.00" length="8.72" width="2.50" shape="2343.53,2864.82 2345.88,2864.32 2347.40,2863.59 2348.92,2862.85 2351.26,2862.31"/>
    </edge>
    <edge id=":cluster_gneJ6_gneJ7_0" function="internal">
        <lane id=":cluster_gneJ6_gneJ7_0_0" index="0" disallow="pedestrian bicycle tram rail_urban rail rail_electric rail_fast ship" speed="60.00" length="7.92" width="2.50" shape="2326.87,2877.09 2334.12,2875.90"/>
        <lane id=":cluster_gneJ6_gneJ7_0_1" index="1" disallow="pedestrian bicycle tram rail_urban rail rail_electric rail_fast ship" speed="60.00" length="7.92" width="2.50" shape="2326.41,2874.63 2333.85,2873.41"/>
        <lane id=":cluster_gneJ6_gneJ7_0_2" index="2" disallow="pedestrian bicycle tram rail_urban rail rail_electric rail_fast ship" speed="60.00" length="7.92" width="2.50" shape="2325.94,2872.17 2333.58,2870.93"/>
        <lane id=":cluster_gneJ6_gneJ7_0_3" index="3" disallow="pedestrian bicycle tram rail_urban rail rail_electric rail_fast ship" speed="60.00" length="7.92" width="2.50" shape="2325.94,2872.17 2328.23,2871.33 2329.61,2870.19 2331.00,2869.11 2333.31,2868.44"/>
        <lane id=":cluster_gneJ6_gneJ7_0_4" index="4" disallow="pedestrian bicycle tram rail_urban rail rail_electric rail_fast ship" speed="60.00" length="7.92" width="2.50" shape="2325.48,2869.72 2327.82,2868.86 2329.24,2867.71 2330.67,2866.63 2333.04,2865.96"/>
    </edge>
    <edge id=":ravindara_bharathi_junction_0" function="internal">
        <lane id=":ravindara_bharathi_junction_0_0" index="0" disallow="pedestrian bicycle tram rail_urban rail rail_electric rail_fast ship" speed="21.40" length="32.72" width="2.50" shape="2385.74,2822.63 2379.63,2830.33 2375.64,2836.38 2370.79,2840.74 2362.05,2843.35"/>
    </edge>
    <edge id=":ravindara_bharathi_junction_1" function="internal">
        <lane id=":ravindara_bharathi_junction_1_0" index="0" disallow="pedestrian bicycle tram rail_urban rail rail_electric rail_fast ship" speed="21.82" length="34.01" width="2.50" shape="2387.33,2824.58 2380.93,2832.54 2376.69,2838.73 2371.55,2843.15 2362.42,2845.82"/>
    </edge>
    <edge id=":ravindara_bharathi_junction_2" function="internal">
        <lane id=":ravindara_bharathi_junction_2_0" index="0" disallow="pedestrian bicycle tram rail_urban rail rail_electric rail_fast ship" speed="22.23" length="35.31" width="2.50" shape="2388.93,2826.53 2382.23,2834.75 2377.74,2841.08 2372.31,2845.57 2362.79,2848.30"/>
    </edge>
    <edge id=":ravindara_bharathi_junction_3" function="internal">
        <lane id=":ravindara_bharathi_junction_3_0" index="0" disallow="pedestrian bicycle tram rail_urban rail rail_electric rail_fast ship" speed="22.63" length="36.62" width="2.50" shape="2390.52,2828.48 2383.54,2836.97 2378.79,2843.42 2373.07,2847.98 2363.15,2850.77"/>
    </edge>
    <edge id=":ravindara_bharathi_junction_4" function="internal">
        <lane id=":ravindara_bharathi_junction_4_0" index="0" disallow="pedestrian bicycle tram rail_urban rail rail_electric rail_fast ship" speed="23.03" length="37.93" width="2.50" shape="2392.11,2830.43 2384.84,2839.18 2379.84,2845.77 2373.84,2850.40 2363.52,2853.24"/>
    </edge>
    <edge id=":ravindara_bharathi_junction_5" function="internal">
        <lane id=":ravindara_bharathi_junction_5_0" index="0" disallow="pedestrian bicycle tram rail_urban rail rail_electric rail_fast ship" speed="32.29" length="48.76" width="2.50" shape="2392.11,2830.43 2382.69,2841.85 2378.42,2851.23 2376.32,2861.80 2373.39,2876.76"/>
        <lane id=":ravindara_bharathi_junction_5_1" index="1" disallow="pedestrian bicycle tram rail_urban rail rail_electric rail_fast ship" speed="31.78" length="48.76" width="2.50" shape="2393.70,2832.38 2384.62,2843.45 2380.57,2852.57 2378.62,2862.84 2375.82,2877.34"/>
        <lane id=":ravindara_bharathi_junction_5_2" index="2" disallow="pedestrian bicycle tram rail_urban rail rail_electric rail_fast ship" speed="31.72" length="48.76" width="2.50" shape="2393.70,2832.38 2385.04,2843.52 2381.81,2852.88 2380.67,2863.37 2378.25,2877.92"/>
        <lane id=":ravindara_bharathi_junction_5_3" index="3" disallow="pedestrian bicycle tram rail_urban rail rail_electric rail_fast ship" speed="31.21" length="48.76" width="2.50" shape="2395.29,2834.33 2386.97,2845.12 2383.96,2854.22 2382.97,2864.41 2380.68,2878.50"/>
        <lane id=":ravindara_bharathi_junction_5_4" index="4" disallow="pedestrian bicycle tram rail_urban rail rail_electric rail_fast ship" speed="30.69" length="48.76" width="2.50" shape="2396.89,2836.29 2388.89,2846.73 2386.11,2855.56 2385.27,2865.44 2383.11,2879.08"/>
    </edge>
    <edge id=":ravindara_bharathi_junction_10" function="internal">
        <lane id=":ravindara_bharathi_junction_10_0" index="0" disallow="pedestrian bicycle tram rail_urban rail rail_electric rail_fast ship" speed="5.91" length="15.80" width="2.50" shape="2396.89,2836.29 2395.45,2840.94 2396.12,2843.89 2398.87,2845.13 2403.73,2844.66"/>
    </edge>
    <edge id=":ravindara_bharathi_junction_11" function="internal">
        <lane id=":ravindara_bharathi_junction_11_0" index="0" disallow="pedestrian bicycle tram rail_urban rail rail_electric rail_fast ship" speed="20.61" length="33.64" width="2.50" shape="2401.29,2883.40 2402.16,2873.32 2402.11,2865.79 2403.83,2859.32 2410.05,2852.41"/>
    </edge>
    <edge id=":ravindara_bharathi_junction_12" function="internal">
        <lane id=":ravindara_bharathi_junction_12_0" index="0" disallow="pedestrian bicycle tram rail_urban rail rail_electric rail_fast ship" speed="14.54" length="62.07" width="2.50" shape="2398.86,2882.82 2399.24,2865.36 2393.04,2853.81 2380.72,2848.14 2362.79,2848.30"/>
    </edge>
    <edge id=":ravindara_bharathi_junction_13" function="internal">
        <lane id=":ravindara_bharathi_junction_13_0" index="0" disallow="pedestrian bicycle tram rail_urban rail rail_electric rail_fast ship" speed="14.25" length="59.65" width="2.50" shape="2398.86,2882.82 2399.07,2866.21 2392.74,2855.51 2380.55,2850.45 2363.15,2850.77"/>
    </edge>
    <edge id=":ravindara_bharathi_junction_14" function="internal">
        <lane id=":ravindara_bharathi_junction_14_0" index="0" disallow="pedestrian bicycle tram rail_urban rail rail_electric rail_fast ship" speed="13.64" length="54.52" width="2.50" shape="2396.42,2882.24 2396.57,2867.11 2390.70,2857.42 2379.46,2852.90 2363.52,2853.24"/>
    </edge>
    <edge id=":ravindara_bharathi_junction_15" function="internal">
        <lane id=":ravindara_bharathi_junction_15_0" index="0" disallow="pedestrian bicycle tram rail_urban rail rail_electric rail_fast ship" speed="13.00" length="49.40" width="2.50" shape="2393.99,2881.67 2394.08,2868.00 2388.66,2859.34 2378.38,2855.35 2363.89,2855.72"/>
    </edge>
    <edge id=":ravindara_bharathi_junction_16" function="internal">
        <lane id=":ravindara_bharathi_junction_16_0" index="0" disallow="pedestrian bicycle tram rail_urban rail rail_electric rail_fast ship" speed="5.93" length="16.32" width="2.50" shape="2393.99,2881.67 2392.24,2876.94 2389.84,2874.93 2386.80,2875.65 2383.11,2879.08"/>
    </edge>
    <edge id=":ravindara_bharathi_junction_17" function="internal">
        <lane id=":ravindara_bharathi_junction_17_0" index="0" disallow="pedestrian bicycle tram rail_urban rail rail_electric rail_fast ship" speed="31.95" length="45.79" width="2.50" shape="2366.05,2870.32 2380.23,2868.04 2389.94,2865.58 2398.71,2861.01 2410.05,2852.41"/>
        <lane id=":ravindara_bharathi_junction_17_1" index="1" disallow="pedestrian bicycle tram rail_urban rail rail_electric rail_fast ship" speed="31.50" length="45.79" width="2.50" shape="2365.68,2867.85 2379.47,2865.63 2388.91,2863.25 2397.44,2858.83 2408.47,2850.48"/>
        <lane id=":ravindara_bharathi_junction_17_2" index="2" disallow="pedestrian bicycle tram rail_urban rail rail_electric rail_fast ship" speed="31.04" length="45.79" width="2.50" shape="2365.32,2865.37 2378.71,2863.23 2387.89,2860.93 2396.17,2856.64 2406.89,2848.54"/>
        <lane id=":ravindara_bharathi_junction_17_3" index="3" disallow="pedestrian bicycle tram rail_urban rail rail_electric rail_fast ship" speed="30.58" length="45.79" width="2.50" shape="2364.95,2862.90 2377.95,2860.83 2386.86,2858.61 2394.91,2854.46 2405.31,2846.60"/>
        <lane id=":ravindara_bharathi_junction_17_4" index="4" disallow="pedestrian bicycle tram rail_urban rail rail_electric rail_fast ship" speed="30.12" length="45.79" width="2.50" shape="2364.58,2860.43 2377.19,2858.42 2385.83,2856.29 2393.64,2852.28 2403.73,2844.66"/>
    </edge>
    <edge id=":ravindara_bharathi_junction_22" function="internal">
        <lane id=":ravindara_bharathi_junction_22_0" index="0" disallow="pedestrian bicycle tram rail_urban rail rail_electric rail_fast ship" speed="4.10" length="6.96" width="2.50" shape="2364.58,2860.43 2366.18,2858.99 2366.59,2857.72 2365.83,2856.63 2363.89,2855.72"/>
    </edge>

    <edge id="207693436#6" from="cluster_gneJ6_gneJ7" to="7721233577" name="Lakdikapul Road" priority="13" type="highway.trunk" spreadType="center" shape="2331.72,2871.13 2348.34,2869.33">
        <lane id="207693436#6_0" index="0" disallow="pedestrian bicycle tram rail_urban rail rail_electric rail_fast ship" speed="60.00" length="10.55" width="2.50" shape="2334.12,2875.90 2344.61,2874.76">
            <param key="origId" value="207693436"/>
        </lane>
        <lane id="207693436#6_1" index="1" disallow="pedestrian bicycle tram rail_urban rail rail_electric rail_fast ship" speed="60.00" length="10.55" width="2.50" shape="2333.85,2873.41 2344.34,2872.28">
            <param key="origId" value="207693436"/>
        </lane>
        <lane id="207693436#6_2" index="2" disallow="pedestrian bicycle tram rail_urban rail rail_electric rail_fast ship" speed="60.00" length="10.55" width="2.50" shape="2333.58,2870.93 2344.07,2869.79">
            <param key="origId" value="207693436"/>
        </lane>
        <lane id="207693436#6_3" index="3" disallow="pedestrian bicycle tram rail_urban rail rail_electric rail_fast ship" speed="60.00" length="10.55" width="2.50" shape="2333.31,2868.44 2343.80,2867.31">
            <param key="origId" value="207693436"/>
        </lane>
        <lane id="207693436#6_4" index="4" disallow="pedestrian bicycle tram rail_urban rail rail_electric rail_fast ship" speed="60.00" length="10.55" width="2.50" shape="2333.04,2865.96 2343.53,2864.82">
            <param key="origId" value="207693436"/>
        </lane>
        <param key="ref" value="NH65;NH163"/>
    </edge>
    <edge id="207693436#7" from="7721233577" to="ravindara_bharathi_junction" name="Lakdikapul Road" priority="13" type="highway.trunk" spreadType="center" shape="2348.22,2867.73 2359.40,2866.33 2368.88,2864.80">
        <lane id="207693436#7_0" index="0" disallow="pedestrian bicycle tram rail_urban rail rail_electric rail_fast ship" speed="60.00" length="13.10" width="2.50" shape="2353.44,2872.11 2360.11,2871.28 2366.05,2870.32">
            <param key="origId" value="207693436"/>
        </lane>
        <lane id="207693436#7_1" index="1" disallow="pedestrian bicycle tram rail_urban rail rail_electric rail_fast ship" speed="60.00" length="13.10" width="2.50" shape="2352.90,2869.66 2359.75,2868.81 2365.68,2867.85">
            <param key="origId" value="207693436"/>
        </lane>
        <lane id="207693436#7_2" index="2" disallow="pedestrian bicycle tram rail_urban rail rail_electric rail_fast ship" speed="60.00" length="13.10" width="2.50" shape="2352.35,2867.21 2359.40,2866.33 2365.32,2865.37">
            <param key="origId" value="207693436"/>
        </lane>
        <lane id="207693436#7_3" index="3" disallow="pedestrian bicycle tram rail_urban rail rail_electric rail_fast ship" speed="60.00" length="13.10" width="2.50" shape="2351.81,2864.76 2359.05,2863.85 2364.95,2862.90">
            <param key="origId" value="207693436"/>
        </lane>
        <lane id="207693436#7_4" index="4" disallow="pedestrian bicycle tram rail_urban rail rail_electric rail_fast ship" speed="60.00" length="13.10" width="2.50" shape="2351.26,2862.31 2358.69,2861.38 2364.58,2860.43">
            <param key="origId" value="207693436"/>
        </lane>
        <param key="origTo" value="308769395"/>
        <param key="ref" value="NH65;NH163"/>
    </edge>
    <edge id="311371526" from="7721233577" to="2177311061" priority="13" type="highway.trunk_link" spreadType="center" shape="2348.83,2875.71 2352.49,2874.89 2354.89,2874.89 2357.08,2874.99 2359.07,2875.20 2360.86,2875.54 2362.45,2876.01 2363.84,2876.61 2365.05,2877.37 2366.08,2878.27 2366.92,2879.34 2367.59,2880.57 2368.09,2881.99 2368.43,2883.59 2368.60,2885.38 2368.61,2887.38 2368.47,2889.58 2368.18,2892.01 2367.74,2894.66">
        <lane id="311371526_0" index="0" disallow="pedestrian bicycle tram rail_urban rail rail_electric rail_fast ship" speed="22.22" length="15.87" shape="2354.06,2874.89 2354.89,2874.89 2357.08,2874.99 2359.07,2875.20 2360.86,2875.54 2362.45,2876.01 2363.84,2876.61 2365.05,2877.37 2366.08,2878.27 2366.92,2879.34 2367.59,2880.57 2367.69,2880.85">
            <param key="origId" value="311371526"/>
        </lane>
    </edge>
    <edge id="313220790#0" from="ravindara_bharathi_junction" to="2177311061" name="AG Office Road" priority="13" type="highway.trunk" spreadType="center" shape="2378.25,2877.92 2378.20,2878.13 2374.03,2895.85">
        <lane id="313220790#0_0" index="0" disallow="pedestrian bicycle tram rail_urban rail rail_electric rail_fast ship" speed="60.00" length="4.72" width="2.50" shape="2373.39,2876.76 2373.33,2876.98 2372.30,2881.37">
            <param key="origId" value="313220790"/>
        </lane>
        <lane id="313220790#0_1" index="1" disallow="pedestrian bicycle tram rail_urban rail rail_electric rail_fast ship" speed="60.00" length="4.72" width="2.50" shape="2375.82,2877.34 2375.77,2877.56 2374.74,2881.94">
            <param key="origId" value="313220790"/>
        </lane>
        <lane id="313220790#0_2" index="2" disallow="pedestrian bicycle tram rail_urban rail rail_electric rail_fast ship" speed="60.00" length="4.72" width="2.50" shape="2378.25,2877.92 2378.20,2878.13 2377.17,2882.51">
            <param key="origId" value="313220790"/>
        </lane>
        <lane id="313220790#0_3" index="3" disallow="pedestrian bicycle tram rail_urban rail rail_electric rail_fast ship" speed="60.00" length="4.72" width="2.50" shape="2380.68,2878.50 2380.63,2878.70 2379.60,2883.08">
            <param key="origId" value="313220790"/>
        </lane>
        <lane id="313220790#0_4" index="4" disallow="pedestrian bicycle tram rail_urban rail rail_electric rail_fast ship" speed="60.00" length="4.72" width="2.50" shape="2383.11,2879.08 2383.07,2879.28 2382.04,2883.66">
            <param key="origId" value="313220790"/>
        </lane>
        <param key="origFrom" value="308769395"/>
        <param key="ref" value="NH44"/>
    </edge>
    <edge id="iqbalminar_entry" from="726181798" to="ravindara_bharathi_junction" name="AG Office Road" priority="13" type="highway.trunk" length="200.00" shape="2354.07,3087.03 2393.17,2879.25">
        <lane id="iqbalminar_entry_0" index="0" disallow="pedestrian bicycle tram rail_urban rail rail_electric rail_fast ship" speed="30.00" length="200.00" width="2.50" shape="2362.67,3088.65 2401.29,2883.40">
            <param key="origId" value="45058013 432358587"/>
        </lane>
        <lane id="iqbalminar_entry_1" index="1" disallow="pedestrian bicycle tram rail_urban rail rail_electric rail_fast ship" speed="30.00" length="200.00" width="2.50" shape="2360.21,3088.19 2398.86,2882.82">
            <param key="origId" value="45058013 432358587"/>
        </lane>
        <lane id="iqbalminar_entry_2" index="2" disallow="pedestrian bicycle tram rail_urban rail rail_electric rail_fast ship" speed="30.00" length="200.00" width="2.50" shape="2357.76,3087.72 2396.42,2882.24">
            <param key="origId" value="45058013 432358587"/>
        </lane>
        <lane id="iqbalminar_entry_3" index="3" disallow="pedestrian bicycle tram rail_urban rail rail_electric rail_fast ship" speed="30.00" length="200.00" width="2.50" shape="2355.30,3087.26 2393.99,2881.67">
            <param key="origId" value="45058013 432358587"/>
        </lane>
        <param key="origTo" value="2177311110"/>
        <param key="ref" value="NH44"/>
    </edge>
    <edge id="iqbalminar_exit" from="2177311061" to="3191288131" name="AG Office Road" priority="13" type="highway.trunk" spreadType="center" length="100.00" shape="2372.46,2895.55 2348.87,2975.11">
        <lane id="iqbalminar_exit_0" index="0" disallow="pedestrian bicycle tram rail_urban rail rail_electric rail_fast ship" speed="60.00" length="100.00" width="2.50" acceleration="1" shape="2366.47,2893.77 2342.88,2973.33">
            <param key="origId" value="313220790"/>
        </lane>
        <lane id="iqbalminar_exit_1" index="1" disallow="pedestrian bicycle tram rail_urban rail rail_electric rail_fast ship" speed="60.00" length="100.00" width="2.50" shape="2368.86,2894.48 2345.27,2974.04">
            <param key="origId" value="313220790"/>
        </lane>
        <lane id="iqbalminar_exit_2" index="2" disallow="pedestrian bicycle tram rail_urban rail rail_electric rail_fast ship" speed="60.00" length="100.00" width="2.50" shape="2371.26,2895.19 2347.67,2974.75">
            <param key="origId" value="313220790"/>
        </lane>
        <lane id="iqbalminar_exit_3" index="3" disallow="pedestrian bicycle tram rail_urban rail rail_electric rail_fast ship" speed="60.00" length="100.00" width="2.50" shape="2373.66,2895.91 2350.07,2975.47">
            <param key="origId" value="313220790"/>
        </lane>
        <lane id="iqbalminar_exit_4" index="4" disallow="pedestrian bicycle tram rail_urban rail rail_electric rail_fast ship" speed="60.00" length="100.00" width="2.50" shape="2376.06,2896.62 2352.47,2976.18">
            <param key="origId" value="313220790"/>
        </lane>
        <lane id="iqbalminar_exit_5" index="5" disallow="pedestrian bicycle tram rail_urban rail rail_electric rail_fast ship" speed="60.00" length="100.00" width="2.50" shape="2378.45,2897.33 2354.86,2976.89">
            <param key="origId" value="313220790"/>
        </lane>
        <param key="ref" value="NH44"/>
    </edge>
    <edge id="oldpssaifabad_entry" from="2550414436" to="cluster_gneJ6_gneJ7" name="Lakdikapul Road" priority="13" type="highway.trunk" shape="2094.15,2912.27 2327.03,2868.15">
        <lane id="oldpssaifabad_entry_0" index="0" disallow="pedestrian bicycle tram rail_urban rail rail_electric rail_fast ship" speed="60.00" length="235.21" width="2.50" shape="2095.78,2920.87 2326.87,2877.09">
            <param key="origId" value="207693436"/>
        </lane>
        <lane id="oldpssaifabad_entry_1" index="1" disallow="pedestrian bicycle tram rail_urban rail rail_electric rail_fast ship" speed="60.00" length="235.21" width="2.50" shape="2095.31,2918.41 2326.41,2874.63">
            <param key="origId" value="207693436"/>
        </lane>
        <lane id="oldpssaifabad_entry_2" index="2" disallow="pedestrian bicycle tram rail_urban rail rail_electric rail_fast ship" speed="60.00" length="235.21" width="2.50" shape="2094.85,2915.95 2325.94,2872.17">
            <param key="origId" value="207693436"/>
        </lane>
        <lane id="oldpssaifabad_entry_3" index="3" disallow="pedestrian bicycle tram rail_urban rail rail_electric rail_fast ship" speed="60.00" length="235.21" width="2.50" shape="2094.38,2913.50 2325.48,2869.72">
            <param key="origId" value="207693436"/>
        </lane>
        <param key="ref" value="NH65;NH163"/>
    </edge>
    <edge id="oldpssaifabad_exit" from="ravindara_bharathi_junction" to="2179449120" name="Lakdikapul Road" priority="13" type="highway.trunk" spreadType="center" shape="2367.18,2848.91 2344.79,2852.23 2209.94,2873.33">
        <lane id="oldpssaifabad_exit_0" index="0" disallow="pedestrian bicycle tram rail_urban rail rail_electric rail_fast ship" speed="60.00" length="154.87" width="2.50" shape="2362.05,2843.35 2343.85,2846.05 2208.97,2867.16">
            <param key="origId" value="45058078"/>
        </lane>
        <lane id="oldpssaifabad_exit_1" index="1" disallow="pedestrian bicycle tram rail_urban rail rail_electric rail_fast ship" speed="60.00" length="154.87" width="2.50" shape="2362.42,2845.82 2344.23,2848.52 2209.36,2869.63">
            <param key="origId" value="45058078"/>
        </lane>
        <lane id="oldpssaifabad_exit_2" index="2" disallow="pedestrian bicycle tram rail_urban rail rail_electric rail_fast ship" speed="60.00" length="154.87" width="2.50" shape="2362.79,2848.30 2344.60,2850.99 2209.75,2872.10">
            <param key="origId" value="45058078"/>
        </lane>
        <lane id="oldpssaifabad_exit_3" index="3" disallow="pedestrian bicycle tram rail_urban rail rail_electric rail_fast ship" speed="60.00" length="154.87" width="2.50" shape="2363.15,2850.77 2344.98,2853.47 2210.13,2874.56">
            <param key="origId" value="45058078"/>
        </lane>
        <lane id="oldpssaifabad_exit_4" index="4" disallow="pedestrian bicycle tram rail_urban rail rail_electric rail_fast ship" speed="60.00" length="154.87" width="2.50" shape="2363.52,2853.24 2345.35,2855.94 2210.52,2877.03">
            <param key="origId" value="45058078"/>
        </lane>
        <lane id="oldpssaifabad_exit_5" index="5" disallow="pedestrian bicycle tram rail_urban rail rail_electric rail_fast ship" speed="60.00" length="154.87" width="2.50" shape="2363.89,2855.72 2345.73,2858.41 2210.91,2879.50">
            <param key="origId" value="45058078"/>
        </lane>
        <param key="origFrom" value="289917156"/>
        <param key="ref" value="NH65;NH163"/>
    </edge>
    <edge id="pcr_entry" from="3249147651" to="ravindara_bharathi_junction" name="Public Garden Road" priority="13" type="highway.trunk" shape="2584.29,2643.27 2395.24,2839.80">
        <lane id="pcr_entry_0" index="0" disallow="pedestrian bicycle tram rail_urban rail rail_electric rail_fast ship" speed="60.00" length="267.97" width="2.50" shape="2570.78,2630.27 2385.74,2822.63">
            <param key="origId" value="313221673"/>
        </lane>
        <lane id="pcr_entry_1" index="1" disallow="pedestrian bicycle tram rail_urban rail rail_electric rail_fast ship" speed="60.00" length="267.97" width="2.50" shape="2572.58,2632.00 2387.33,2824.58">
            <param key="origId" value="313221673"/>
        </lane>
        <lane id="pcr_entry_2" index="2" disallow="pedestrian bicycle tram rail_urban rail rail_electric rail_fast ship" speed="60.00" length="267.97" width="2.50" shape="2574.38,2633.74 2388.93,2826.53">
            <param key="origId" value="313221673"/>
        </lane>
        <lane id="pcr_entry_3" index="3" disallow="pedestrian bicycle tram rail_urban rail rail_electric rail_fast ship" speed="60.00" length="267.97" width="2.50" shape="2576.18,2635.47 2390.52,2828.48">
            <param key="origId" value="313221673"/>
        </lane>
        <lane id="pcr_entry_4" index="4" disallow="pedestrian bicycle tram rail_urban rail rail_electric rail_fast ship" speed="60.00" length="267.97" width="2.50" shape="2577.98,2637.20 2392.11,2830.43">
            <param key="origId" value="313221673"/>
        </lane>
        <lane id="pcr_entry_5" index="5" disallow="pedestrian bicycle tram rail_urban rail rail_electric rail_fast ship" speed="60.00" length="267.97" width="2.50" shape="2579.79,2638.94 2393.70,2832.38">
            <param key="origId" value="313221673"/>
        </lane>
        <lane id="pcr_entry_6" index="6" disallow="pedestrian bicycle tram rail_urban rail rail_electric rail_fast ship" speed="60.00" length="267.97" width="2.50" shape="2581.59,2640.67 2395.29,2834.33">
            <param key="origId" value="313221673"/>
        </lane>
        <lane id="pcr_entry_7" index="7" disallow="pedestrian bicycle tram rail_urban rail rail_electric rail_fast ship" speed="60.00" length="267.97" width="2.50" shape="2583.39,2642.40 2396.89,2836.29">
            <param key="origId" value="313221673"/>
        </lane>
        <param key="origTo" value="289917156"/>
        <param key="ref" value="NH44;NH65;NH163"/>
    </edge>
    <edge id="pcr_exit" from="ravindara_bharathi_junction" to="7721233575" priority="13" type="highway.trunk" spreadType="center" shape="2405.02,2850.06 2477.55,2790.92">
        <lane id="pcr_exit_0" index="0" disallow="pedestrian bicycle tram rail_urban rail rail_electric rail_fast ship" speed="60.00" length="91.18" width="2.50" shape="2410.05,2852.41 2480.71,2794.80">
            <param key="origId" value="28109575"/>
        </lane>
        <lane id="pcr_exit_1" index="1" disallow="pedestrian bicycle tram rail_urban rail rail_electric rail_fast ship" speed="60.00" length="91.18" width="2.50" shape="2408.47,2850.48 2479.13,2792.86">
            <param key="origId" value="28109575"/>
        </lane>
        <lane id="pcr_exit_2" index="2" disallow="pedestrian bicycle tram rail_urban rail rail_electric rail_fast ship" speed="60.00" length="91.18" width="2.50" shape="2406.89,2848.54 2477.55,2790.92">
            <param key="origId" value="28109575"/>
        </lane>
        <lane id="pcr_exit_3" index="3" disallow="pedestrian bicycle tram rail_urban rail rail_electric rail_fast ship" speed="60.00" length="91.18" width="2.50" shape="2405.31,2846.60 2475.97,2788.98">
            <param key="origId" value="28109575"/>
        </lane>
        <lane id="pcr_exit_4" index="4" disallow="pedestrian bicycle tram rail_urban rail rail_electric rail_fast ship" speed="60.00" length="91.18" width="2.50" shape="2403.73,2844.66 2474.39,2787.04">
            <param key="origId" value="28109575"/>
        </lane>
        <param key="origFrom" value="2422989108"/>
        <param key="ref" value="NH65;NH163;NH44"/>
    </edge>

    <tlLogic id="cluster_2177311110_2422989108_289917156_308769395" type="delay_based" programID="0" offset="0">
        <phase duration="19" state="GGGGGGGGGGGGrrrrrrrrrrr" name="pcr"/>
        <phase duration="11" state="GGGGGYYYYYYGrrrrrrrrrrr" name="amber0"/>
        <phase duration="19" state="GGGGgrrrrrrGGGGGGrrrrrr" name="iqbalminar"/>
        <phase duration="11" state="GGGGgrrrrrrGYYYYYrrrrrr" name="amber1"/>
        <phase duration="19" state="GGGGGrrrrrrgrrrrrGGGGGG" name="oldpssaifabad"/>
        <phase duration="11" state="GGGGGrrrrrrGrrrryYYYYYY" name="amber2"/>
    </tlLogic>

    <junction id="2177311061" type="priority" x="2374.03" y="2895.85" incLanes="311371526_0 313220790#0_0 313220790#0_1 313220790#0_2 313220790#0_3 313220790#0_4" intLanes=":2177311061_0_0 :2177311061_1_0 :2177311061_1_1 :2177311061_1_2 :2177311061_1_3 :2177311061_1_4" shape="2365.81,2880.64 2369.46,2881.05 2371.08,2881.08 2383.25,2883.94 2379.65,2897.68 2365.27,2893.42 2366.02,2890.59 2366.50,2888.04 2366.72,2885.77 2366.68,2883.78 2366.38,2882.07">
        <request index="0" response="000000" foes="000000" cont="0"/>
        <request index="1" response="000000" foes="000000" cont="0"/>
        <request index="2" response="000000" foes="000000" cont="0"/>
        <request index="3" response="000000" foes="000000" cont="0"/>
        <request index="4" response="000000" foes="000000" cont="0"/>
        <request index="5" response="000000" foes="000000" cont="0"/>
    </junction>
    <junction id="2179449120" type="dead_end" x="2209.94" y="2873.33" incLanes="oldpssaifabad_exit_0 oldpssaifabad_exit_1 oldpssaifabad_exit_2 oldpssaifabad_exit_3 oldpssaifabad_exit_4 oldpssaifabad_exit_5" intLanes="" shape="2208.78,2865.92 2211.10,2880.74"/>
    <junction id="2422989207" type="dead_end" x="2606.17" y="1693.08" incLanes="" intLanes="" shape="2606.17,1693.08"/>
    <junction id="2550414436" type="dead_end" x="2094.15" y="2912.27" incLanes="" intLanes="" shape="2094.15,2912.27 2096.01,2922.10"/>
    <junction id="3191288131" type="dead_end" x="2350.43" y="2975.47" incLanes="iqbalminar_exit_0 iqbalminar_exit_1 iqbalminar_exit_2 iqbalminar_exit_3 iqbalminar_exit_4 iqbalminar_exit_5" intLanes="" shape="2341.71,2972.88 2356.09,2977.15"/>
    <junction id="3249147651" type="dead_end" x="2584.29" y="2643.27" incLanes="" intLanes="" shape="2584.29,2643.27 2569.88,2629.40"/>
    <junction id="5787787988" type="dead_end" x="0.00" y="6455.61" incLanes="" intLanes="" shape="0.00,6455.61"/>
    <junction id="6800005227" type="dead_end" x="5037.24" y="0.00" incLanes="" intLanes="" shape="5037.24,0.00"/>
    <junction id="726181798" type="dead_end" x="2354.07" y="3087.03" incLanes="" intLanes="" shape="2354.07,3087.03 2363.90,3088.88"/>
    <junction id="7721233575" type="dead_end" x="2477.55" y="2790.92" incLanes="pcr_exit_0 pcr_exit_1 pcr_exit_2 pcr_exit_3 pcr_exit_4" intLanes="" shape="2481.50,2795.76 2473.60,2786.08"/>
    <junction id="7721233577" type="priority" x="2348.22" y="2867.73" incLanes="207693436#6_0 207693436#6_1 207693436#6_2 207693436#6_3 207693436#6_4" intLanes=":7721233577_0_0 :7721233577_1_0 :7721233577_1_1 :7721233577_1_2 :7721233577_1_3 :7721233577_1_4" shape="2350.99,2861.08 2354.42,2876.49 2352.36,2876.42 2350.83,2876.25 2349.57,2876.05 2348.32,2875.90 2346.80,2875.86 2344.74,2876.01 2343.40,2863.58 2346.25,2862.85 2347.19,2862.36 2348.14,2861.86 2349.32,2861.41">
        <request index="0" response="000000" foes="000000" cont="0"/>
        <request index="1" response="000000" foes="000000" cont="0"/>
        <request index="2" response="000000" foes="000000" cont="0"/>
        <request index="3" response="000000" foes="000000" cont="0"/>
        <request index="4" response="000000" foes="000000" cont="0"/>
        <request index="5" response="000000" foes="000000" cont="0"/>
    </junction>
    <junction id="cluster_gneJ6_gneJ7" type="priority" x="2329.38" y="2869.64" incLanes="oldpssaifabad_entry_0 oldpssaifabad_entry_1 oldpssaifabad_entry_2 oldpssaifabad_entry_3" intLanes=":cluster_gneJ6_gneJ7_0_0 :cluster_gneJ6_gneJ7_0_1 :cluster_gneJ6_gneJ7_0_2 :cluster_gneJ6_gneJ7_0_3 :cluster_gneJ6_gneJ7_0_4" shape="2332.91,2864.71 2334.25,2877.14 2327.11,2878.31 2325.25,2868.49 2328.15,2867.26 2329.06,2866.48 2329.97,2865.72 2331.16,2865.10">
        <request index="0" response="00000" foes="00000" cont="0"/>
        <request index="1" response="00000" foes="00000" cont="0"/>
        <request index="2" response="00000" foes="00000" cont="0"/>
        <request index="3" response="00000" foes="00000" cont="0"/>
        <request index="4" response="00000" foes="00000" cont="0"/>
    </junction>
    <junction id="ravindara_bharathi_junction" type="traffic_light" x="2392.42" y="2856.59" incLanes="pcr_entry_0 pcr_entry_1 pcr_entry_2 pcr_entry_3 pcr_entry_4 pcr_entry_5 pcr_entry_6 pcr_entry_7 iqbalminar_entry_0 iqbalminar_entry_1 iqbalminar_entry_2 iqbalminar_entry_3 207693436#7_0 207693436#7_1 207693436#7_2 207693436#7_3 207693436#7_4" intLanes=":ravindara_bharathi_junction_0_0 :ravindara_bharathi_junction_1_0 :ravindara_bharathi_junction_2_0 :ravindara_bharathi_junction_3_0 :ravindara_bharathi_junction_4_0 :ravindara_bharathi_junction_5_0 :ravindara_bharathi_junction_5_1 :ravindara_bharathi_junction_5_2 :ravindara_bharathi_junction_5_3 :ravindara_bharathi_junction_5_4 :ravindara_bharathi_junction_10_0 :ravindara_bharathi_junction_11_0 :ravindara_bharathi_junction_12_0 :ravindara_bharathi_junction_13_0 :ravindara_bharathi_junction_14_0 :ravindara_bharathi_junction_15_0 :ravindara_bharathi_junction_16_0 :ravindara_bharathi_junction_17_0 :ravindara_bharathi_junction_17_1 :ravindara_bharathi_junction_17_2 :ravindara_bharathi_junction_17_3 :ravindara_bharathi_junction_17_4 :ravindara_bharathi_junction_22_0" shape="2384.95,2821.65 2410.84,2853.38 2406.19,2858.00 2403.91,2862.22 2403.20,2866.47 2403.25,2871.18 2403.29,2876.77 2402.51,2883.69 2372.17,2876.47 2372.16,2873.21 2371.41,2872.19 2370.18,2871.57 2368.45,2871.36 2366.24,2871.56 2361.87,2842.12 2368.13,2840.59 2372.26,2838.27 2375.12,2835.20 2377.60,2831.39 2380.58,2826.87">
        <request index="0"  response="00000000000000000000000" foes="00000001111000000000000" cont="0"/>
        <request index="1"  response="00000000000000000000000" foes="00000001111000000000000" cont="0"/>
        <request index="2"  response="00000000000000000000000" foes="00000001111000000000000" cont="0"/>
        <request index="3"  response="00000000000000000000000" foes="00000001111000000000000" cont="0"/>
        <request index="4"  response="00000000000000000000000" foes="00000001111000000000000" cont="0"/>
        <request index="5"  response="00000000000000000000000" foes="01111111111000000000000" cont="0"/>
        <request index="6"  response="00000000000000000000000" foes="01111111111000000000000" cont="0"/>
        <request index="7"  response="00000000000000000000000" foes="01111111111000000000000" cont="0"/>
        <request index="8"  response="00000000000000000000000" foes="01111111111000000000000" cont="0"/>
        <request index="9"  response="00000000000000000000000" foes="01111111111000000000000" cont="0"/>
        <request index="10" response="01111100000000000000000" foes="01111100000000000000000" cont="0"/>
        <request index="11" response="00000000000000000000000" foes="01111100000000000000000" cont="0"/>
        <request index="12" response="00000000000001111111111" foes="11111100000001111111111" cont="0"/>
        <request index="13" response="00000000000001111111111" foes="11111100000001111111111" cont="0"/>
        <request index="14" response="00000000000001111111111" foes="11111100000001111111111" cont="0"/>
        <request index="15" response="00000000000001111111111" foes="11111100000001111111111" cont="0"/>
        <request index="16" response="00000000000001111100000" foes="00000000000001111100000" cont="0"/>
        <request index="17" response="00000001111101111100000" foes="00000001111111111100000" cont="0"/>
        <request index="18" response="00000001111101111100000" foes="00000001111111111100000" cont="0"/>
        <request index="19" response="00000001111101111100000" foes="00000001111111111100000" cont="0"/>
        <request index="20" response="00000001111101111100000" foes="00000001111111111100000" cont="0"/>
        <request index="21" response="00000001111101111100000" foes="00000001111111111100000" cont="0"/>
        <request index="22" response="00000001111000000000000" foes="00000001111000000000000" cont="0"/>
    </junction>

    <connection from="207693436#6" to="311371526" fromLane="0" toLane="0" keepClear="0" via=":7721233577_0_0" dir="R" state="M"/>
    <connection from="207693436#6" to="207693436#7" fromLane="0" toLane="0" via=":7721233577_1_0" dir="s" state="M"/>
    <connection from="207693436#6" to="207693436#7" fromLane="1" toLane="1" keepClear="0" via=":7721233577_1_1" dir="s" state="M"/>
    <connection from="207693436#6" to="207693436#7" fromLane="2" toLane="2" keepClear="0" via=":7721233577_1_2" dir="s" state="M"/>
    <connection from="207693436#6" to="207693436#7" fromLane="3" toLane="3" keepClear="0" via=":7721233577_1_3" dir="s" state="M"/>
    <connection from="207693436#6" to="207693436#7" fromLane="4" toLane="4" keepClear="0" via=":7721233577_1_4" dir="s" state="M"/>
    <connection from="207693436#7" to="pcr_exit" fromLane="0" toLane="0" via=":ravindara_bharathi_junction_17_0" tl="cluster_2177311110_2422989108_289917156_308769395" linkIndex="17" dir="s" state="o"/>
    <connection from="207693436#7" to="pcr_exit" fromLane="1" toLane="1" via=":ravindara_bharathi_junction_17_1" tl="cluster_2177311110_2422989108_289917156_308769395" linkIndex="18" dir="s" state="o"/>
    <connection from="207693436#7" to="pcr_exit" fromLane="2" toLane="2" via=":ravindara_bharathi_junction_17_2" tl="cluster_2177311110_2422989108_289917156_308769395" linkIndex="19" dir="s" state="o"/>
    <connection from="207693436#7" to="pcr_exit" fromLane="3" toLane="3" via=":ravindara_bharathi_junction_17_3" tl="cluster_2177311110_2422989108_289917156_308769395" linkIndex="20" dir="s" state="o"/>
    <connection from="207693436#7" to="pcr_exit" fromLane="4" toLane="4" via=":ravindara_bharathi_junction_17_4" tl="cluster_2177311110_2422989108_289917156_308769395" linkIndex="21" dir="s" state="o"/>
    <connection from="207693436#7" to="oldpssaifabad_exit" fromLane="4" toLane="5" via=":ravindara_bharathi_junction_22_0" tl="cluster_2177311110_2422989108_289917156_308769395" linkIndex="22" dir="T" state="o"/>
    <connection from="311371526" to="iqbalminar_exit" fromLane="0" toLane="0" keepClear="0" via=":2177311061_0_0" dir="s" state="M"/>
    <connection from="313220790#0" to="iqbalminar_exit" fromLane="0" toLane="1" keepClear="0" via=":2177311061_1_0" dir="s" state="M"/>
    <connection from="313220790#0" to="iqbalminar_exit" fromLane="1" toLane="2" keepClear="0" via=":2177311061_1_1" dir="s" state="M"/>
    <connection from="313220790#0" to="iqbalminar_exit" fromLane="2" toLane="3" keepClear="0" via=":2177311061_1_2" dir="s" state="M"/>
    <connection from="313220790#0" to="iqbalminar_exit" fromLane="3" toLane="4" keepClear="0" via=":2177311061_1_3" dir="s" state="M"/>
    <connection from="313220790#0" to="iqbalminar_exit" fromLane="4" toLane="5" keepClear="0" via=":2177311061_1_4" dir="s" state="M"/>
    <connection from="iqbalminar_entry" to="pcr_exit" fromLane="0" toLane="0" via=":ravindara_bharathi_junction_11_0" tl="cluster_2177311110_2422989108_289917156_308769395" linkIndex="11" dir="s" state="O"/>
    <connection from="iqbalminar_entry" to="oldpssaifabad_exit" fromLane="1" toLane="2" via=":ravindara_bharathi_junction_12_0" tl="cluster_2177311110_2422989108_289917156_308769395" linkIndex="12" dir="r" state="o"/>
    <connection from="iqbalminar_entry" to="oldpssaifabad_exit" fromLane="1" toLane="3" via=":ravindara_bharathi_junction_13_0" tl="cluster_2177311110_2422989108_289917156_308769395" linkIndex="13" dir="r" state="o"/>
    <connection from="iqbalminar_entry" to="oldpssaifabad_exit" fromLane="2" toLane="4" via=":ravindara_bharathi_junction_14_0" tl="cluster_2177311110_2422989108_289917156_308769395" linkIndex="14" dir="r" state="o"/>
    <connection from="iqbalminar_entry" to="oldpssaifabad_exit" fromLane="3" toLane="5" via=":ravindara_bharathi_junction_15_0" tl="cluster_2177311110_2422989108_289917156_308769395" linkIndex="15" dir="r" state="o"/>
    <connection from="iqbalminar_entry" to="313220790#0" fromLane="3" toLane="4" via=":ravindara_bharathi_junction_16_0" tl="cluster_2177311110_2422989108_289917156_308769395" linkIndex="16" dir="T" state="o"/>
    <connection from="oldpssaifabad_entry" to="207693436#6" fromLane="0" toLane="0" keepClear="0" via=":cluster_gneJ6_gneJ7_0_0" dir="s" state="M"/>
    <connection from="oldpssaifabad_entry" to="207693436#6" fromLane="1" toLane="1" keepClear="0" via=":cluster_gneJ6_gneJ7_0_1" dir="s" state="M"/>
    <connection from="oldpssaifabad_entry" to="207693436#6" fromLane="2" toLane="2" via=":cluster_gneJ6_gneJ7_0_2" dir="s" state="M"/>
    <connection from="oldpssaifabad_entry" to="207693436#6" fromLane="2" toLane="3" keepClear="0" via=":cluster_gneJ6_gneJ7_0_3" dir="s" state="M"/>
    <connection from="oldpssaifabad_entry" to="207693436#6" fromLane="3" toLane="4" keepClear="0" via=":cluster_gneJ6_gneJ7_0_4" dir="s" state="M"/>
    <connection from="pcr_entry" to="oldpssaifabad_exit" fromLane="0" toLane="0" via=":ravindara_bharathi_junction_0_0" tl="cluster_2177311110_2422989108_289917156_308769395" linkIndex="0" dir="L" state="O"/>
    <connection from="pcr_entry" to="oldpssaifabad_exit" fromLane="1" toLane="1" via=":ravindara_bharathi_junction_1_0" tl="cluster_2177311110_2422989108_289917156_308769395" linkIndex="1" dir="L" state="O"/>
    <connection from="pcr_entry" to="oldpssaifabad_exit" fromLane="2" toLane="2" via=":ravindara_bharathi_junction_2_0" tl="cluster_2177311110_2422989108_289917156_308769395" linkIndex="2" dir="L" state="O"/>
    <connection from="pcr_entry" to="oldpssaifabad_exit" fromLane="3" toLane="3" via=":ravindara_bharathi_junction_3_0" tl="cluster_2177311110_2422989108_289917156_308769395" linkIndex="3" dir="L" state="O"/>
    <connection from="pcr_entry" to="oldpssaifabad_exit" fromLane="4" toLane="4" via=":ravindara_bharathi_junction_4_0" tl="cluster_2177311110_2422989108_289917156_308769395" linkIndex="4" dir="L" state="O"/>
    <connection from="pcr_entry" to="313220790#0" fromLane="4" toLane="0" via=":ravindara_bharathi_junction_5_0" tl="cluster_2177311110_2422989108_289917156_308769395" linkIndex="5" dir="s" state="O"/>
    <connection from="pcr_entry" to="313220790#0" fromLane="5" toLane="1" via=":ravindara_bharathi_junction_5_1" tl="cluster_2177311110_2422989108_289917156_308769395" linkIndex="6" dir="s" state="O"/>
    <connection from="pcr_entry" to="313220790#0" fromLane="5" toLane="2" via=":ravindara_bharathi_junction_5_2" tl="cluster_2177311110_2422989108_289917156_308769395" linkIndex="7" dir="s" state="O"/>
    <connection from="pcr_entry" to="313220790#0" fromLane="6" toLane="3" via=":ravindara_bharathi_junction_5_3" tl="cluster_2177311110_2422989108_289917156_308769395" linkIndex="8" dir="s" state="O"/>
    <connection from="pcr_entry" to="313220790#0" fromLane="7" toLane="4" via=":ravindara_bharathi_junction_5_4" tl="cluster_2177311110_2422989108_289917156_308769395" linkIndex="9" dir="s" state="O"/>
    <connection from="pcr_entry" to="pcr_exit" fromLane="7" toLane="4" via=":ravindara_bharathi_junction_10_0" tl="cluster_2177311110_2422989108_289917156_308769395" linkIndex="10" dir="T" state="o"/>

    <connection from=":2177311061_0" to="iqbalminar_exit" fromLane="0" toLane="0" dir="s" state="M"/>
    <connection from=":2177311061_1" to="iqbalminar_exit" fromLane="0" toLane="1" dir="s" state="M"/>
    <connection from=":2177311061_1" to="iqbalminar_exit" fromLane="1" toLane="2" dir="s" state="M"/>
    <connection from=":2177311061_1" to="iqbalminar_exit" fromLane="2" toLane="3" dir="s" state="M"/>
    <connection from=":2177311061_1" to="iqbalminar_exit" fromLane="3" toLane="4" dir="s" state="M"/>
    <connection from=":2177311061_1" to="iqbalminar_exit" fromLane="4" toLane="5" dir="s" state="M"/>
    <connection from=":7721233577_0" to="311371526" fromLane="0" toLane="0" dir="R" state="M"/>
    <connection from=":7721233577_1" to="207693436#7" fromLane="0" toLane="0" dir="s" state="M"/>
    <connection from=":7721233577_1" to="207693436#7" fromLane="1" toLane="1" dir="s" state="M"/>
    <connection from=":7721233577_1" to="207693436#7" fromLane="2" toLane="2" dir="s" state="M"/>
    <connection from=":7721233577_1" to="207693436#7" fromLane="3" toLane="3" dir="s" state="M"/>
    <connection from=":7721233577_1" to="207693436#7" fromLane="4" toLane="4" dir="s" state="M"/>
    <connection from=":cluster_gneJ6_gneJ7_0" to="207693436#6" fromLane="0" toLane="0" dir="s" state="M"/>
    <connection from=":cluster_gneJ6_gneJ7_0" to="207693436#6" fromLane="1" toLane="1" dir="s" state="M"/>
    <connection from=":cluster_gneJ6_gneJ7_0" to="207693436#6" fromLane="2" toLane="2" dir="s" state="M"/>
    <connection from=":cluster_gneJ6_gneJ7_0" to="207693436#6" fromLane="3" toLane="3" dir="s" state="M"/>
    <connection from=":cluster_gneJ6_gneJ7_0" to="207693436#6" fromLane="4" toLane="4" dir="s" state="M"/>
    <connection from=":ravindara_bharathi_junction_0" to="oldpssaifabad_exit" fromLane="0" toLane="0" dir="L" state="M"/>
    <connection from=":ravindara_bharathi_junction_1" to="oldpssaifabad_exit" fromLane="0" toLane="1" dir="L" state="M"/>
    <connection from=":ravindara_bharathi_junction_2" to="oldpssaifabad_exit" fromLane="0" toLane="2" dir="L" state="M"/>
    <connection from=":ravindara_bharathi_junction_3" to="oldpssaifabad_exit" fromLane="0" toLane="3" dir="L" state="M"/>
    <connection from=":ravindara_bharathi_junction_4" to="oldpssaifabad_exit" fromLane="0" toLane="4" dir="L" state="M"/>
    <connection from=":ravindara_bharathi_junction_5" to="313220790#0" fromLane="0" toLane="0" dir="s" state="M"/>
    <connection from=":ravindara_bharathi_junction_5" to="313220790#0" fromLane="1" toLane="1" dir="s" state="M"/>
    <connection from=":ravindara_bharathi_junction_5" to="313220790#0" fromLane="2" toLane="2" dir="s" state="M"/>
    <connection from=":ravindara_bharathi_junction_5" to="313220790#0" fromLane="3" toLane="3" dir="s" state="M"/>
    <connection from=":ravindara_bharathi_junction_5" to="313220790#0" fromLane="4" toLane="4" dir="s" state="M"/>
    <connection from=":ravindara_bharathi_junction_10" to="pcr_exit" fromLane="0" toLane="4" dir="T" state="M"/>
    <connection from=":ravindara_bharathi_junction_11" to="pcr_exit" fromLane="0" toLane="0" dir="s" state="M"/>
    <connection from=":ravindara_bharathi_junction_12" to="oldpssaifabad_exit" fromLane="0" toLane="2" dir="r" state="M"/>
    <connection from=":ravindara_bharathi_junction_13" to="oldpssaifabad_exit" fromLane="0" toLane="3" dir="r" state="M"/>
    <connection from=":ravindara_bharathi_junction_14" to="oldpssaifabad_exit" fromLane="0" toLane="4" dir="r" state="M"/>
    <connection from=":ravindara_bharathi_junction_15" to="oldpssaifabad_exit" fromLane="0" toLane="5" dir="r" state="M"/>
    <connection from=":ravindara_bharathi_junction_16" to="313220790#0" fromLane="0" toLane="4" dir="T" state="M"/>
    <connection from=":ravindara_bharathi_junction_17" to="pcr_exit" fromLane="0" toLane="0" dir="s" state="M"/>
    <connection from=":ravindara_bharathi_junction_17" to="pcr_exit" fromLane="1" toLane="1" dir="s" state="M"/>
    <connection from=":ravindara_bharathi_junction_17" to="pcr_exit" fromLane="2" toLane="2" dir="s" state="M"/>
    <connection from=":ravindara_bharathi_junction_17" to="pcr_exit" fromLane="3" toLane="3" dir="s" state="M"/>
    <connection from=":ravindara_bharathi_junction_17" to="pcr_exit" fromLane="4" toLane="4" dir="s" state="M"/>
    <connection from=":ravindara_bharathi_junction_22" to="oldpssaifabad_exit" fromLane="0" toLane="5" dir="T" state="M"/>

</net>
